CPU/EXU.v
module EXU (
        input wire [4:0] op,                // 操作码
        input wire [31:0] regaData,         // 源寄存器 A 数据
        input wire [31:0] regbData,         // 源寄存器 B 数据
        input wire  regcWr_i,               // 写使能
        input wire [4:0] regcAddr_i,        // 寄存器写地址

        output reg [31:0] regcData,         // 写数据
        output reg [4:0] regcAddr,         // 运算结果
        output reg regcWr                   // 写使能
    );

    assign regcWr = regcWr_i;
    assign regcAddr = regcAddr_i;


    // ALU
    // 定义: op
    // 5'd0: 加法
    // 5'd1: 减法
    // 5'd2: 与
    // 5'd3: 或
    // 5'd4: 异或
    // 5'd5: 逻辑左移
    // 5'd6: 逻辑右移
    // 5'd7: 算数右移

    always @(*) begin
        case (op)
            5'd0: // 加法
                regcData = regaData + regbData;
            5'd1: // 减法
                regcData = regaData - regbData;
            5'd2: // 与
                regcData = regaData & regbData;
            5'd3: // 或
                regcData = regaData | regbData;
            5'd4: // 异或
                regcData = regaData ^ regbData;
            5'd5: // 逻辑左移
                regcData = regaData << regbData;
            5'd6: // 逻辑右移
                regcData = regaData >> regbData;
            5'd7: // 算术右移
                regcData = regaData >>> regbData;

            default:
                regcData = 32'b0;
        endcase
    end

endmodule

CPU/IDU.v
// 符号扩展宏：signExtend(num, n)
`define signExtend(num, n)  {{(32 - n){num[n-1]}}, num}

// 零扩展宏：zeroExtend(num, n)
`define zeroExtend(num, n)  {{(32 - n){1'b0}}, num}

module IDU (
        input wire rst,               // 复位信号

        input wire [31:0] pc,
        input wire [31:0] inst,             // 输入指令
        input wire [31:0] regaData_i,       // 寄存器 A 数据
        input wire [31:0] regbData_i,       // 寄存器 B 数据, 这个输出还要负责处理立即数的传递

        output reg jCe,                    // 跳转使能
        output reg [31:0] jAddr,            // 跳转地址，为了利用 case 语法特性，这里使用 reg

        output reg [4:0] op,               // 计算类型，不是简单的 opcode ,为了利用 case 语法特性，这里使用 reg
        output reg [31:0] regaData,        // 源寄存器 A 数据
        output reg [31:0] regbData,        // 源寄存器 B 数据,为了利用 case 语法特性，这里使用 reg
        output reg  regcWr_i,              // 写使能信号
        output reg [4:0] regcAddr_i,       // 目标寄存器地址

        // 连接 RegFile
        output wire  regaRd,                // 读使能
        output wire [4:0] regaAddr,         // 读地址 a
        output wire  regbRd,                // 读使能
        output wire [4:0] regbAddr          // 读地址 b
    );
    // 提取指令字段

    // 默认 指令存储器 使能为 1
    assign regaRd = 1'b1;
    assign regbRd = 1'b1;

    wire [5:0] funct = inst[5:0];
    wire [5:0] opcode = inst[31:26];
    wire [4:0] rs = inst[25:21];
    wire [4:0] rt = inst[20:16];
    wire [4:0] rd = inst[15:11];
    wire [15:0] imm = inst[15:0]; // 也是 offset
    wire [25:0] target = inst[25:0];


    // 跳转信号
    // 跳转信号
    always @(*) begin
        case (opcode)
            6'b000010: // j
                jCe = 1'b1;
            6'b000011: // jal
                jCe = 1'b1;
            6'b000100: // beq
                jCe = (regaData_i == regbData_i); // rs 和 rt 寄存器中的值相等时跳转
            6'b000101: // bne
                jCe = (regaData_i != regbData_i); // rs 和 rt 寄存器中的值不相等时跳转
            default:
                jCe = 1'b0;
        endcase
    end


    // 跳转地址
    always @(*) begin
        case (opcode)
            6'b000010: // j
                jAddr = {pc[31:28], target, 2'b00};
            6'b000011: // jal
                jAddr = {pc[31:28], target, 2'b00};
            6'b000100: // beq
                jAddr = `signExtend({imm << 2}, 16) + pc;
            6'b0000101: // bne
                jAddr = `signExtend({imm << 2}, 16) + pc;
            default:
                jAddr = 32'b0;
        endcase
    end


    // 第一操作数
    always @(*) begin
        case (opcode)
            6'b000011: // jal
                regaData = pc;
            6'b000010: // j
                regaData = 32'd0;
            6'b000100: // beq
                regaData = 32'd0;
            6'b000101: // bne
                regaData = 32'd0;
            default:
                regaData = regaData_i;
        endcase
    end

    // 第二操作数
    always @(*) begin
        case (opcode)
            6'b001000: // addi
                regbData = `signExtend(imm, 16);
            6'b001100: // andi
                regbData = `signExtend(imm, 16);
            6'b001101: // ori
                regbData = `signExtend(imm, 16);
            6'b001110: // xori
                regbData = `signExtend(imm, 16);
            6'b000011: // jal
                regbData = 32'd4;
            6'b000010: // j
                regbData = 32'd0;
            6'b000100: // beq
                regbData = 32'd0;
            6'b000101: // bne
                regbData = 32'd0;
            default:
                regbData = regbData_i;
        endcase
    end
    // 寄存器写使能信号
    // 多路选择器
    always @(*) begin
        case (opcode)
            6'b000000: // R 型指令
                regcWr_i = 1'b1;
            6'b001000: // addi
                regcWr_i = 1'b1;
            6'b001100: // andi
                regcWr_i = 1'b1;
            6'b001101: // ori
                regcWr_i = 1'b1;
            6'b001110: //xori
                regcWr_i = 1'b1;
            6'b000011: // jal
                regcWr_i = 1'b1;
            default:
                regcWr_i = 1'b0;
        endcase
    end
    // 寄存器写地址
    always @(*) begin
        case (opcode)
            6'b000000: // R 型指令
                regcAddr_i = rd;
            6'b000011: // jal
                regcAddr_i = 5'd31;
            default:
                regcAddr_i = rt;
        endcase
    end

    // ALU
    // 定义 op
    // 5'd0: 加法
    // 5'd1: 减法
    // 5'd2: 与
    // 5'd3: 或
    // 5'd4: 异或
    // 5'd5: 逻辑左移
    // 5'd6: 逻辑右移
    // 5'd7: 算数右移

    // ALU：对于每一类或者一个命令，导向到 ALU 中的具体的操作
    always @(*) begin
        case (opcode)
            6'b000000: // R 型指令
            begin
                case (funct[5:0])
                    6'b100000: // add
                        op = 5'd0;
                    6'b100010: //sub
                        op = 5'd1;
                    6'b100100: // and
                        op = 5'd2;
                    6'b100101: // or
                        op = 5'd3;
                    6'b100110: // xor
                        op = 5'd4;
                    6'b000000: // sll
                        op = 5'd5;
                    6'b000010: // srl
                        op = 5'd6;
                    6'b000011: // sra
                        op = 5'd7;
                    default:
                        op = 5'd0;
                endcase
            end

            6'b001000: // addi
                op = 5'd0;
            6'b001100: // andi
                op = 5'd2;
            6'b001101: // ori
                op = 5'd3;
            6'b001110: // xori
                op = 5'd4;
            6'b000011: // jal，使用加法
                op = 5'd0;
            default:
                op = 5'd0;
        endcase
    end


    // RegFile 地址
    assign regaAddr = rs;
    assign regbAddr = rt;

endmodule

CPU/RegFile.v
module RegFile (
        input wire clk,               // 时钟信号
        input wire rst,               // 复位信号

        // to IDU
        output wire [31:0] regaData,  // 读端口 A 数据
        output wire [31:0] regbData,  // 读端口 B 数据

        // from IDU
        input wire [4:0] regaAddr,    // 读端口 A 地址
        input wire regaRd,        // 读使能
        input wire [4:0] regbAddr,    // 读端口 B 地址
        input wire  regbRd,        // 读使能

        // from EXU
        input wire we,                // 写使能
        input wire [4:0] wAddr,       // 写地址
        input wire [31:0] wData      // 写数据
    );

    reg [31:0] registers [31:0];  // 32 个 32 位寄存器

    // 读操作
    assign regaData = (regaRd) ? registers[regaAddr] : 32'b0;
    assign regbData = (regbRd) ? registers[regbAddr] : 32'b0;

    // 写操作
    always @(posedge clk or posedge rst) begin
        if (rst) begin
            registers[0] <= 32'b0;
            registers[1] <= 32'b0;
            registers[2] <= 32'b0;
            registers[3] <= 32'b0;
            registers[4] <= 32'b0;
            registers[5] <= 32'b0;
            registers[6] <= 32'b0;
            registers[7] <= 32'b0;
            registers[8] <= 32'b0;
            registers[9] <= 32'b0;
            registers[10] <= 32'b0;
            registers[11] <= 32'b0;
            registers[12] <= 32'b0;
            registers[13] <= 32'b0;
            registers[14] <= 32'b0;
            registers[15] <= 32'b0;
            registers[16] <= 32'b0;
            registers[17] <= 32'b0;
            registers[18] <= 32'b0;
            registers[19] <= 32'b0;
            registers[20] <= 32'b0;
            registers[21] <= 32'b0;
            registers[22] <= 32'b0;
            registers[23] <= 32'b0;
            registers[24] <= 32'b0;
            registers[25] <= 32'b0;
            registers[26] <= 32'b0;
            registers[27] <= 32'b0;
            registers[28] <= 32'b0;
            registers[29] <= 32'b0;
            registers[30] <= 32'b0;
            registers[31] <= 32'b0;

        end
        else if (we) begin
            registers[wAddr] <= wData;  // 写操作
        end
    end

endmodule

CPU/InstMem.v
module InstMem (
        input wire ce,                // 存储器使能信号
        input wire [31:0] addr,       // 取指地址
        output wire [31:0] data       // 输出指令数据
    );

    reg [31:0] mem [0:1023];      // 1024 个 32 位的存储单元

    initial begin
        mem[0] = 32'h340800FF; // ORI $8, $0, 0xFF
        mem[1] = 32'h3409FF00; // ORI $9, $0, 0xFF00

        mem[2] = 32'h300A00FF; // ANDI $10, $0, 0xFF
        mem[3] = 32'h300BFF00; // ANDI $11, $0, 0xFF00

        mem[4] = 32'h200C0001; // ADDI $12, $0, 1
        mem[5] = 32'h200DFFFF; // ADDI $13, $0, -1

        mem[6] = 32'h240E0002; // SUBI $14, $0, 2 (using pseudo-instruction: ADDI $14, $0, -2)
        mem[7] = 32'h240FFFFE; // SUBI $15, $0, -2

        mem[8] = 32'h3C100003; // LUI $16, 0x0003
        mem[9] = 32'h3C1100FF; // LUI $17, 0x00FF

        mem[10] = 32'h02124024; // AND $8, $16, $18
        mem[11] = 32'h02314824; // AND $9, $17, $19

        mem[12] = 32'h02125026; // XOR $10, $16, $18
        mem[13] = 32'h02315826; // XOR $11, $17, $19

        mem[14] = 32'h02126020; // ADD $12, $16, $18
        mem[15] = 32'h02316820; // ADD $13, $17, $19

        mem[16] = 32'h02127022; // SUB $14, $16, $18
        mem[17] = 32'h02317822; // SUB $15, $17, $19

        mem[18] = 32'h00104080; // SLL $8, $8, 2
        mem[19] = 32'h00104880; // SLL $9, $9, 2

        mem[20] = 32'h00105082; // SRL $10, $10, 2
        mem[21] = 32'h00105882; // SRL $11, $11, 2

        mem[22] = 32'h00106083; // SRA $12, $12, 2
        mem[23] = 32'h00106883; // SRA $13, $13, 2

        // 测试 BEQ (当 $16 和 $17 相等时跳转)
        mem[24] = 32'h12110001; // BEQ $16, $17, offset=1 (跳转到 mem[25])

        // 测试 BNE (当 $16 和 $17 不相等时跳转)
        mem[25] = 32'h16110001; // BNE $16, $17, offset=1 (跳转到 mem[26])

        // 设置寄存器值使得 BEQ 和 BNE 测试通过
        // BEQ 跳转
        mem[26] = 32'h34010000; // ORI $1, $0, 0x0000 (设置 $16 = $17)，BEQ 跳转成立
        mem[27] = 32'h3402FFFF; // ORI $2, $0, 0xFFFF

        // 测试 JAL (跳转到指定地址并保存返回地址)
        mem[28] = 32'h0C000004; // JAL 4 (跳转到地址 4，并将返回地址存入 $31)

        // 测试 J (无条件跳转到 4)
        mem[29] = 32'h08000001; // J 4 (跳转到地址 4)

        // 设置跳转测试寄存器值，确保 J 跳转成功
        mem[30] = 32'h34080001; // ORI $8, $0, 0x01

        // 无条件跳转到 0 号指令
        mem[31] = 32'h08000000; // J 0 (跳转到地址 0)
    end



    assign data = (ce == 1'b1) ? mem[addr[11:2]] : 32'b0; // 地址对齐，非使能输出 0

endmodule

CPU/IFU.v
module IFU (
        input wire clk,               // 时钟信号
        input wire rst,               // 复位信号
        input wire [31:0] jAddr, 	  // 跳转地址
        input wire jCe, 		      // 跳转使能
        output reg [31:0] pc,         // 程序计数器
        output wire romCe            // 指令存储器使能信号
    );

    // 状态机,使用时序电路
    // 指令存储器使能信号生成
    assign romCe = !rst;  // 复位时不使能指令存储器

    // 程序计数器更新
    always @(posedge clk or posedge rst) begin
        if (rst) begin
            pc <= 32'h0;  // 复位时PC归零
        end
        else if (jCe) begin
            pc <= jAddr;  // 跳转时，直接使用跳转地址
        end
        else begin
            pc <= pc + 32'd4;  // 默认情况下，PC+4
        end
    end


endmodule

CPU/CPU.v
module CPU (
        input wire clk,
        input wire rst
    );
    // 信号连线
    // IFU
    wire [31:0] ifu_pc;
    wire ifu_romCe;

    // IDU
    wire idu_jCe;
    wire [31:0] idu_jAddr;
    wire [4:0] idu_op;
    wire [31:0] idu_regaData;
    wire [31:0] idu_regbData;
    wire  idu_regcWr_i;
    wire [4:0] idu_regcAddr_i;

    wire  idu_regaRd;
    wire [4:0] idu_regaAddr;

    wire  idu_regbRd;
    wire [4:0] idu_regbAddr;

    // EXU
    wire  [31:0] exu_regcData;
    wire [4:0] exu_regcAddr;
    wire exu_regcWr;

    // InstMem
    wire [31:0] instMem_data;

    // RegFile
    wire [31:0] regs_regaData;
    wire [31:0] regs_regbData;

    IFU ifu(
            .clk(clk),
            .rst(rst),
            .jAddr(idu_jAddr),
            .jCe(idu_jCe),
            .pc(ifu_pc),
            .romCe(ifu_romCe)
        );

    InstMem instMem(
                .ce(ifu_romCe),
                .addr(ifu_pc),
                .data(instMem_data)
            );
    RegFile regs(
                .clk(clk),
                .rst(rst),
                .regaData(regs_regaData),
                .regbData(regs_regbData),
                .regaAddr(idu_regaAddr),
                .regaRd(idu_regaRd),
                .regbAddr(idu_regbAddr),
                .regbRd(idu_regbRd),
                .we(exu_regcWr),
                .wAddr(exu_regcAddr),
                .wData(exu_regcData)
            );

    IDU idu(
            .rst(rst),
            .pc(ifu_pc),
            .inst(instMem_data),
            .regaData_i(regs_regaData),
            .regbData_i(regs_regbData),

            .jCe(idu_jCe),
            .jAddr(idu_jAddr),
            .op(idu_op),
            .regaData(idu_regaData),
            .regbData(idu_regbData),
            .regcWr_i(idu_regcWr_i),
            .regcAddr_i(idu_regcAddr_i),
            .regaRd(idu_regaRd),
            .regaAddr(idu_regaAddr),
            .regbRd(idu_regbRd),
            .regbAddr(idu_regbAddr)
        );

    EXU exu(
            .op(idu_op),
            .regaData(idu_regaData),
            .regbData(idu_regbData),
            .regcWr_i(idu_regcWr_i),
            .regcAddr_i(idu_regcAddr_i),
            .regcData(exu_regcData),
            .regcAddr(exu_regcAddr),
            .regcWr(exu_regcWr)
        );



endmodule

wave.vcd
$version Generated by VerilatedVcd $end
$timescale 1s $end

 $scope module TOP $end
  $var wire  1 Q clk $end
  $var wire  1 R rst $end
  $scope module CPU $end
   $var wire  1 Q clk $end
   $var wire  5 T exu_regcAddr [4:0] $end
   $var wire 32 * exu_regcData [31:0] $end
   $var wire  1 ( exu_regcWr $end
   $var wire 32 $ idu_jAddr [31:0] $end
   $var wire  1 # idu_jCe $end
   $var wire  5 % idu_op [4:0] $end
   $var wire  5 U idu_regaAddr [4:0] $end
   $var wire 32 & idu_regaData [31:0] $end
   $var wire  1 Y idu_regaRd $end
   $var wire  5 ) idu_regbAddr [4:0] $end
   $var wire 32 ' idu_regbData [31:0] $end
   $var wire  1 Y idu_regbRd $end
   $var wire  5 T idu_regcAddr_i [4:0] $end
   $var wire  1 ( idu_regcWr_i $end
   $var wire 32 0 ifu_pc [31:0] $end
   $var wire  1 S ifu_romCe $end
   $var wire 32 V instMem_data [31:0] $end
   $var wire 32 + regs_regaData [31:0] $end
   $var wire 32 , regs_regbData [31:0] $end
   $var wire  1 R rst $end
   $scope module exu $end
    $var wire  5 % op [4:0] $end
    $var wire 32 & regaData [31:0] $end
    $var wire 32 ' regbData [31:0] $end
    $var wire  5 T regcAddr [4:0] $end
    $var wire  5 T regcAddr_i [4:0] $end
    $var wire 32 * regcData [31:0] $end
    $var wire  1 ( regcWr $end
    $var wire  1 ( regcWr_i $end
   $upscope $end
   $scope module idu $end
    $var wire  6 W funct [5:0] $end
    $var wire 16 . imm [15:0] $end
    $var wire 32 V inst [31:0] $end
    $var wire 32 $ jAddr [31:0] $end
    $var wire  1 # jCe $end
    $var wire  5 % op [4:0] $end
    $var wire  6 - opcode [5:0] $end
    $var wire 32 0 pc [31:0] $end
    $var wire  5 X rd [4:0] $end
    $var wire  5 U regaAddr [4:0] $end
    $var wire 32 & regaData [31:0] $end
    $var wire 32 + regaData_i [31:0] $end
    $var wire  1 Y regaRd $end
    $var wire  5 ) regbAddr [4:0] $end
    $var wire 32 ' regbData [31:0] $end
    $var wire 32 , regbData_i [31:0] $end
    $var wire  1 Y regbRd $end
    $var wire  5 T regcAddr_i [4:0] $end
    $var wire  1 ( regcWr_i $end
    $var wire  5 U rs [4:0] $end
    $var wire  1 R rst $end
    $var wire  5 ) rt [4:0] $end
    $var wire 26 / target [25:0] $end
   $upscope $end
   $scope module ifu $end
    $var wire  1 Q clk $end
    $var wire 32 $ jAddr [31:0] $end
    $var wire  1 # jCe $end
    $var wire 32 0 pc [31:0] $end
    $var wire  1 S romCe $end
    $var wire  1 R rst $end
   $upscope $end
   $scope module instMem $end
    $var wire 32 0 addr [31:0] $end
    $var wire  1 S ce $end
    $var wire 32 V data [31:0] $end
   $upscope $end
   $scope module regs $end
    $var wire  1 Q clk $end
    $var wire  5 U regaAddr [4:0] $end
    $var wire 32 + regaData [31:0] $end
    $var wire  1 Y regaRd $end
    $var wire  5 ) regbAddr [4:0] $end
    $var wire 32 , regbData [31:0] $end
    $var wire  1 Y regbRd $end
    $var wire 32 1 registers[0] [31:0] $end
    $var wire 32 ; registers[10] [31:0] $end
    $var wire 32 < registers[11] [31:0] $end
    $var wire 32 = registers[12] [31:0] $end
    $var wire 32 > registers[13] [31:0] $end
    $var wire 32 ? registers[14] [31:0] $end
    $var wire 32 @ registers[15] [31:0] $end
    $var wire 32 A registers[16] [31:0] $end
    $var wire 32 B registers[17] [31:0] $end
    $var wire 32 C registers[18] [31:0] $end
    $var wire 32 D registers[19] [31:0] $end
    $var wire 32 2 registers[1] [31:0] $end
    $var wire 32 E registers[20] [31:0] $end
    $var wire 32 F registers[21] [31:0] $end
    $var wire 32 G registers[22] [31:0] $end
    $var wire 32 H registers[23] [31:0] $end
    $var wire 32 I registers[24] [31:0] $end
    $var wire 32 J registers[25] [31:0] $end
    $var wire 32 K registers[26] [31:0] $end
    $var wire 32 L registers[27] [31:0] $end
    $var wire 32 M registers[28] [31:0] $end
    $var wire 32 N registers[29] [31:0] $end
    $var wire 32 3 registers[2] [31:0] $end
    $var wire 32 O registers[30] [31:0] $end
    $var wire 32 P registers[31] [31:0] $end
    $var wire 32 4 registers[3] [31:0] $end
    $var wire 32 5 registers[4] [31:0] $end
    $var wire 32 6 registers[5] [31:0] $end
    $var wire 32 7 registers[6] [31:0] $end
    $var wire 32 8 registers[7] [31:0] $end
    $var wire 32 9 registers[8] [31:0] $end
    $var wire 32 : registers[9] [31:0] $end
    $var wire  1 R rst $end
    $var wire  5 T wAddr [4:0] $end
    $var wire 32 * wData [31:0] $end
    $var wire  1 ( we $end
   $upscope $end
  $upscope $end
 $upscope $end
$enddefinitions $end


#0
0#
b00000000000000000000000000000000 $
b00101 %
b00000000000000000000000000000000 &
b00000000000000000000000000000000 '
1(
b00000 )
b00000000000000000000000000000000 *
b00000000000000000000000000000000 +
b00000000000000000000000000000000 ,
b000000 -
b0000000000000000 .
b00000000000000000000000000 /
b00000000000000000000000000000000 0
b00000000000000000000000000000000 1
b00000000000000000000000000000000 2
b00000000000000000000000000000000 3
b00000000000000000000000000000000 4
b00000000000000000000000000000000 5
b00000000000000000000000000000000 6
b00000000000000000000000000000000 7
b00000000000000000000000000000000 8
b00000000000000000000000000000000 9
b00000000000000000000000000000000 :
b00000000000000000000000000000000 ;
b00000000000000000000000000000000 <
b00000000000000000000000000000000 =
b00000000000000000000000000000000 >
b00000000000000000000000000000000 ?
b00000000000000000000000000000000 @
b00000000000000000000000000000000 A
b00000000000000000000000000000000 B
b00000000000000000000000000000000 C
b00000000000000000000000000000000 D
b00000000000000000000000000000000 E
b00000000000000000000000000000000 F
b00000000000000000000000000000000 G
b00000000000000000000000000000000 H
b00000000000000000000000000000000 I
b00000000000000000000000000000000 J
b00000000000000000000000000000000 K
b00000000000000000000000000000000 L
b00000000000000000000000000000000 M
b00000000000000000000000000000000 N
b00000000000000000000000000000000 O
b00000000000000000000000000000000 P
0Q
1R
0S
b00000 T
b00000 U
b00000000000000000000000000000000 V
b000000 W
b00000 X
1Y
#1
1Q
#2
b00011 %
b00000000000000000000000011111111 '
b01000 )
b00000000000000000000000011111111 *
b001101 -
b0000000011111111 .
b00000010000000000011111111 /
0Q
0R
1S
b01000 T
b00110100000010000000000011111111 V
b111111 W
#3
b11111111111111111111111100000000 '
b01001 )
b11111111111111111111111100000000 *
b1111111100000000 .
b00000010011111111100000000 /
b00000000000000000000000000000100 0
b00000000000000000000000011111111 9
1Q
b01001 T
b00110100000010011111111100000000 V
b000000 W
b11111 X
#4
0Q
#5
b00010 %
b00000000000000000000000011111111 '
b01010 )
b00000000000000000000000000000000 *
b001100 -
b0000000011111111 .
b00000010100000000011111111 /
b00000000000000000000000000001000 0
b11111111111111111111111100000000 :
1Q
b01010 T
b00110000000010100000000011111111 V
b111111 W
b00000 X
#6
0Q
#7
b11111111111111111111111100000000 '
b01011 )
b1111111100000000 .
b00000010111111111100000000 /
b00000000000000000000000000001100 0
1Q
b01011 T
b00110000000010111111111100000000 V
b000000 W
b11111 X
#8
0Q
#9
b00000 %
b00000000000000000000000000000001 '
b01100 )
b00000000000000000000000000000001 *
b001000 -
b0000000000000001 .
b00000011000000000000000001 /
b00000000000000000000000000010000 0
1Q
b01100 T
b00100000000011000000000000000001 V
b000001 W
b00000 X
#10
0Q
#11
b11111111111111111111111111111111 '
b01101 )
b11111111111111111111111111111111 *
b1111111111111111 .
b00000011011111111111111111 /
b00000000000000000000000000010100 0
b00000000000000000000000000000001 =
1Q
b01101 T
b00100000000011011111111111111111 V
b111111 W
b11111 X
#12
0Q
#13
b00000000000000000000000000000000 '
0(
b01110 )
b00000000000000000000000000000000 *
b001001 -
b0000000000000010 .
b00000011100000000000000010 /
b00000000000000000000000000011000 0
b11111111111111111111111111111111 >
1Q
b01110 T
b00100100000011100000000000000010 V
b000010 W
b00000 X
#14
0Q
#15
b01111 )
b1111111111111110 .
b00000011111111111111111110 /
b00000000000000000000000000011100 0
1Q
b01111 T
b00100100000011111111111111111110 V
b111110 W
b11111 X
#16
0Q
#17
b10000 )
b001111 -
b0000000000000011 .
b00000100000000000000000011 /
b00000000000000000000000000100000 0
1Q
b10000 T
b00111100000100000000000000000011 V
b000011 W
b00000 X
#18
0Q
#19
b10001 )
b0000000011111111 .
b00000100010000000011111111 /
b00000000000000000000000000100100 0
1Q
b10001 T
b00111100000100010000000011111111 V
b111111 W
#20
0Q
#21
b00010 %
1(
b10010 )
b000000 -
b0100000000100100 .
b10000100100100000000100100 /
b00000000000000000000000000101000 0
1Q
b01000 T
b10000 U
b00000010000100100100000000100100 V
b100100 W
b01000 X
#22
0Q
#23
b10001 )
b0100100000100100 .
b10001100010100100000100100 /
b00000000000000000000000000101100 0
b00000000000000000000000000000000 9
1Q
b01001 T
b10001 U
b00000010001100010100100000100100 V
b01001 X
#24
0Q
#25
b00100 %
b10010 )
b0101000000100110 .
b10000100100101000000100110 /
b00000000000000000000000000110000 0
b00000000000000000000000000000000 :
1Q
b01010 T
b10000 U
b00000010000100100101000000100110 V
b100110 W
b01010 X
#26
0Q
#27
b10001 )
b0101100000100110 .
b10001100010101100000100110 /
b00000000000000000000000000110100 0
1Q
b01011 T
b10001 U
b00000010001100010101100000100110 V
b01011 X
#28
0Q
#29
b00000 %
b10010 )
b0110000000100000 .
b10000100100110000000100000 /
b00000000000000000000000000111000 0
1Q
b01100 T
b10000 U
b00000010000100100110000000100000 V
b100000 W
b01100 X
#30
0Q
#31
b10001 )
b0110100000100000 .
b10001100010110100000100000 /
b00000000000000000000000000111100 0
b00000000000000000000000000000000 =
1Q
b01101 T
b10001 U
b00000010001100010110100000100000 V
b01101 X
#32
0Q
#33
b00001 %
b10010 )
b0111000000100010 .
b10000100100111000000100010 /
b00000000000000000000000001000000 0
b00000000000000000000000000000000 >
1Q
b01110 T
b10000 U
b00000010000100100111000000100010 V
b100010 W
b01110 X
#34
0Q
#35
b10001 )
b0111100000100010 .
b10001100010111100000100010 /
b00000000000000000000000001000100 0
1Q
b01111 T
b10001 U
b00000010001100010111100000100010 V
b01111 X
#36
0Q
#37
b00101 %
b10000 )
b0100000010000000 .
b00000100000100000010000000 /
b00000000000000000000000001001000 0
1Q
b01000 T
b00000 U
b00000000000100000100000010000000 V
b000000 W
b01000 X
#38
0Q
#39
b0100100010000000 .
b00000100000100100010000000 /
b00000000000000000000000001001100 0
1Q
b01001 T
b00000000000100000100100010000000 V
b01001 X
#40
0Q
#41
b00110 %
b0101000010000010 .
b00000100000101000010000010 /
b00000000000000000000000001010000 0
1Q
b01010 T
b00000000000100000101000010000010 V
b000010 W
b01010 X
#42
0Q
#43
b0101100010000010 .
b00000100000101100010000010 /
b00000000000000000000000001010100 0
1Q
b01011 T
b00000000000100000101100010000010 V
b01011 X
#44
0Q
#45
b00111 %
b0110000010000011 .
b00000100000110000010000011 /
b00000000000000000000000001011000 0
1Q
b01100 T
b00000000000100000110000010000011 V
b000011 W
b01100 X
#46
0Q
#47
b0110100010000011 .
b00000100000110100010000011 /
b00000000000000000000000001011100 0
1Q
b01101 T
b00000000000100000110100010000011 V
b01101 X
#48
0Q
#49
1#
b00000000000000000000000001100100 $
b00000 %
0(
b10001 )
b000100 -
b0000000000000001 .
b10000100010000000000000001 /
b00000000000000000000000001100000 0
1Q
b10001 T
b10000 U
b00010010000100010000000000000001 V
b000001 W
b00000 X
#50
0Q
#51
0#
b00000000000000000000000001101000 $
b000101 -
b00000000000000000000000001100100 0
1Q
b00010110000100010000000000000001 V
#52
0Q
#53
b00000000000000000000000000000000 $
b00011 %
1(
b00001 )
b001101 -
b0000000000000000 .
b00000000010000000000000000 /
b00000000000000000000000001101000 0
1Q
b00001 T
b00000 U
b00110100000000010000000000000000 V
b000000 W
#54
0Q
#55
b11111111111111111111111111111111 '
b00010 )
b11111111111111111111111111111111 *
b1111111111111111 .
b00000000101111111111111111 /
b00000000000000000000000001101100 0
1Q
b00010 T
b00110100000000101111111111111111 V
b111111 W
b11111 X
#56
0Q
#57
1#
b00000000000000000000000000010000 $
b00000 %
b00000000000000000000000001110000 &
b00000000000000000000000000000100 '
b00000 )
b00000000000000000000000001110100 *
b000011 -
b0000000000000100 .
b00000000000000000000000100 /
b00000000000000000000000001110000 0
b11111111111111111111111111111111 3
1Q
b11111 T
b00001100000000000000000000000100 V
b000100 W
b00000 X
#58
0Q
#59
0#
b00000000000000000000000000000000 $
b00000000000000000000000000000000 &
b00000000000000000000000000000001 '
b01100 )
b00000000000000000000000000000001 *
b001000 -
b0000000000000001 .
b00000011000000000000000001 /
b00000000000000000000000000010000 0
b00000000000000000000000001110100 P
1Q
b01100 T
b00100000000011000000000000000001 V
b000001 W
#60
0Q
#61
b11111111111111111111111111111111 '
b01101 )
b11111111111111111111111111111111 *
b1111111111111111 .
b00000011011111111111111111 /
b00000000000000000000000000010100 0
b00000000000000000000000000000001 =
1Q
b01101 T
b00100000000011011111111111111111 V
b111111 W
b11111 X
#62
0Q
#63
b00000000000000000000000000000000 '
0(
b01110 )
b00000000000000000000000000000000 *
b001001 -
b0000000000000010 .
b00000011100000000000000010 /
b00000000000000000000000000011000 0
b11111111111111111111111111111111 >
1Q
b01110 T
b00100100000011100000000000000010 V
b000010 W
b00000 X
#64
0Q
#65
b01111 )
b1111111111111110 .
b00000011111111111111111110 /
b00000000000000000000000000011100 0
1Q
b01111 T
b00100100000011111111111111111110 V
b111110 W
b11111 X
#66
0Q
#67
b10000 )
b001111 -
b0000000000000011 .
b00000100000000000000000011 /
b00000000000000000000000000100000 0
1Q
b10000 T
b00111100000100000000000000000011 V
b000011 W
b00000 X
#68
0Q
#69
b10001 )
b0000000011111111 .
b00000100010000000011111111 /
b00000000000000000000000000100100 0
1Q
b10001 T
b00111100000100010000000011111111 V
b111111 W
#70
0Q
#71
b00010 %
1(
b10010 )
b000000 -
b0100000000100100 .
b10000100100100000000100100 /
b00000000000000000000000000101000 0
1Q
b01000 T
b10000 U
b00000010000100100100000000100100 V
b100100 W
b01000 X
#72
0Q
#73
b10001 )
b0100100000100100 .
b10001100010100100000100100 /
b00000000000000000000000000101100 0
1Q
b01001 T
b10001 U
b00000010001100010100100000100100 V
b01001 X
#74
0Q
#75
b00100 %
b10010 )
b0101000000100110 .
b10000100100101000000100110 /
b00000000000000000000000000110000 0
1Q
b01010 T
b10000 U
b00000010000100100101000000100110 V
b100110 W
b01010 X
#76
0Q
#77
b10001 )
b0101100000100110 .
b10001100010101100000100110 /
b00000000000000000000000000110100 0
1Q
b01011 T
b10001 U
b00000010001100010101100000100110 V
b01011 X
#78
0Q
#79
b00000 %
b10010 )
b0110000000100000 .
b10000100100110000000100000 /
b00000000000000000000000000111000 0
1Q
b01100 T
b10000 U
b00000010000100100110000000100000 V
b100000 W
b01100 X
#80
0Q
#81
b10001 )
b0110100000100000 .
b10001100010110100000100000 /
b00000000000000000000000000111100 0
b00000000000000000000000000000000 =
1Q
b01101 T
b10001 U
b00000010001100010110100000100000 V
b01101 X
#82
0Q
#83
b00001 %
b10010 )
b0111000000100010 .
b10000100100111000000100010 /
b00000000000000000000000001000000 0
b00000000000000000000000000000000 >
1Q
b01110 T
b10000 U
b00000010000100100111000000100010 V
b100010 W
b01110 X
#84
0Q
#85
b10001 )
b0111100000100010 .
b10001100010111100000100010 /
b00000000000000000000000001000100 0
1Q
b01111 T
b10001 U
b00000010001100010111100000100010 V
b01111 X
#86
0Q
#87
b00101 %
b10000 )
b0100000010000000 .
b00000100000100000010000000 /
b00000000000000000000000001001000 0
1Q
b01000 T
b00000 U
b00000000000100000100000010000000 V
b000000 W
b01000 X
#88
0Q
#89
b0100100010000000 .
b00000100000100100010000000 /
b00000000000000000000000001001100 0
1Q
b01001 T
b00000000000100000100100010000000 V
b01001 X
#90
0Q
#91
b00110 %
b0101000010000010 .
b00000100000101000010000010 /
b00000000000000000000000001010000 0
1Q
b01010 T
b00000000000100000101000010000010 V
b000010 W
b01010 X
#92
0Q
#93
b0101100010000010 .
b00000100000101100010000010 /
b00000000000000000000000001010100 0
1Q
b01011 T
b00000000000100000101100010000010 V
b01011 X
#94
0Q
